{
  "alexa" : 1000000,
  "deepLinks" : [ ],
  "fileName" : "coursera.json",
  "freesoftware" : false,
  "fulltos" : { },
  "icons" : { },
  "id" : "coursera",
  "jdm" : {
    "name" : "Coursera",
    "url" : "https://www.coursera.org/about/contact",
    "difficulty" : "hard",
    "notes" : "Contact support and request they delete your account."
  },
  "keywords" : [ ],
  "name" : "coursera",
  "pointIds" : [ ],
  "related" : [ ],
  "tosdr" : {
    "keywords" : [ ],
    "rated" : "false",
    "related" : [ ],
    "alexa" : 0
  },
  "type" : "service",
  "urls" : [ ]
}